illuminatio/__init__.py
illuminatio/cleaner.py
illuminatio/host.py
illuminatio/illuminatio.py
illuminatio/illuminatio_runner.py
illuminatio/k8s_util.py
illuminatio/rule.py
illuminatio/test_case.py
illuminatio/test_generator.py
illuminatio/test_orchestrator.py
illuminatio/util.py
illuminatio/manifests/cluster-role.yaml
illuminatio/manifests/runner-daemonset.yaml
illuminatio-1.4.0.dist-info/LICENSE
illuminatio-1.4.0.dist-info/METADATA
illuminatio-1.4.0.dist-info/WHEEL
illuminatio-1.4.0.dist-info/entry_points.txt
illuminatio-1.4.0.dist-info/top_level.txt
illuminatio-1.4.0.dist-info/RECORD
