Metadata-Version: 2.1
Name: illuminatio
Version: 1.4.0
Summary: The kubernetes network policy validator.
Home-page: https://github.com/inovex/illuminatio
Author: inovex GmbH
Author-email: list-ito+illuminatio@inovex.de
License: apache
Platform: any
Classifier: Development Status :: 4 - Beta
Classifier: Programming Language :: Python
Requires-Dist: requests
Requires-Dist: google-auth
Requires-Dist: python-dateutil
Requires-Dist: pyyaml
Requires-Dist: oauthlib
Requires-Dist: kubernetes
Requires-Dist: click
Requires-Dist: click-log
Requires-Dist: docker
Requires-Dist: nsenter
Requires-Dist: attrs
Requires-Dist: pluggy
Requires-Dist: pytest
Requires-Dist: urllib3
Requires-Dist: setuptools
Requires-Dist: termcolor
